CHANGELOG.rst
CONTRIBUTORS.rst
LICENSE.txt
MANIFEST.in
README.rst
setup.py
docs/Makefile
docs/__init__.py
docs/conf.py
docs/index.rst
docs/api/BalancedDiscStorage.rst
docs/api/balanced_disc_storage.rst
docs/api/balanced_disc_storage_z.rst
docs/api/path_and_hash.rst
src/BalancedDiscStorage/__init__.py
src/BalancedDiscStorage/balanced_disc_storage.py
src/BalancedDiscStorage/balanced_disc_storage_z.py
src/BalancedDiscStorage/path_and_hash.py
src/BalancedDiscStorage.egg-info/PKG-INFO
src/BalancedDiscStorage.egg-info/SOURCES.txt
src/BalancedDiscStorage.egg-info/dependency_links.txt
src/BalancedDiscStorage.egg-info/not-zip-safe
src/BalancedDiscStorage.egg-info/requires.txt
src/BalancedDiscStorage.egg-info/top_level.txt
tests/test_a_path_and_hash.py
tests/test_balanced_disc_storage.py
tests/test_balanced_disc_storagez.py
tests/files/a_file
tests/files/aa_file
tests/files/archive.zip
tests/files/b_file
tests/files/sum_founder.py