Metadata-Version: 1.1
Name: BalancedDiscStorage
Version: 1.0.2
Summary: Makes sure, that there are never more files in one directory, than your LIMIT.
Home-page: https://github.com/Bystroushaak/BalancedDiscStorage
Author: Bystroushaak
Author-email: bystrousak@kitakitsune.org
License: MIT
Platform: UNKNOWN
Classifier: Development Status :: 3 - Alpha
Classifier: Programming Language :: Python
Classifier: Programming Language :: Python :: 2.7
Classifier: Intended Audience :: Developers
Classifier: Topic :: Software Development :: Libraries
Classifier: Topic :: Software Development :: Libraries :: Python Modules
Classifier: License :: OSI Approved :: MIT License
